sphinx_proof/__init__.py
sphinx_proof/directive.py
sphinx_proof/domain.py
sphinx_proof/nodes.py
sphinx_proof/proof_type.py
sphinx_proof/_static/proof.css
sphinx_proof/_static/minimal/proof.css
sphinx_proof/translations/__init__.py
sphinx_proof/translations/_convert.py
sphinx_proof/translations/jsons/Algorithm.json
sphinx_proof/translations/jsons/Assumption.json
sphinx_proof/translations/jsons/Axiom.json
sphinx_proof/translations/jsons/Conjecture.json
sphinx_proof/translations/jsons/Corollary.json
sphinx_proof/translations/jsons/Criterion.json
sphinx_proof/translations/jsons/Definition.json
sphinx_proof/translations/jsons/Example.json
sphinx_proof/translations/jsons/Lemma.json
sphinx_proof/translations/jsons/Notation.json
sphinx_proof/translations/jsons/Observation.json
sphinx_proof/translations/jsons/Property.json
sphinx_proof/translations/jsons/Proposition.json
sphinx_proof/translations/jsons/Remark.json
sphinx_proof/translations/jsons/Theorem.json
sphinx_proof/translations/locales/__init__.py
sphinx_proof/translations/locales/ar/LC_MESSAGES/proof.mo
sphinx_proof/translations/locales/bg/LC_MESSAGES/proof.mo
sphinx_proof/translations/locales/bn/LC_MESSAGES/proof.mo
sphinx_proof/translations/locales/cs/LC_MESSAGES/proof.mo
sphinx_proof/translations/locales/da/LC_MESSAGES/proof.mo
sphinx_proof/translations/locales/de/LC_MESSAGES/proof.mo
sphinx_proof/translations/locales/el/LC_MESSAGES/proof.mo
sphinx_proof/translations/locales/es/LC_MESSAGES/proof.mo
sphinx_proof/translations/locales/fa/LC_MESSAGES/proof.mo
sphinx_proof/translations/locales/fi/LC_MESSAGES/proof.mo
sphinx_proof/translations/locales/fr/LC_MESSAGES/proof.mo
sphinx_proof/translations/locales/he/LC_MESSAGES/proof.mo
sphinx_proof/translations/locales/hi/LC_MESSAGES/proof.mo
sphinx_proof/translations/locales/hu/LC_MESSAGES/proof.mo
sphinx_proof/translations/locales/id/LC_MESSAGES/proof.mo
sphinx_proof/translations/locales/it/LC_MESSAGES/proof.mo
sphinx_proof/translations/locales/ja/LC_MESSAGES/proof.mo
sphinx_proof-0.3.0.dist-info/licenses/LICENSE
sphinx_proof-0.3.0.dist-info/METADATA
sphinx_proof-0.3.0.dist-info/WHEEL
sphinx_proof-0.3.0.dist-info/top_level.txt
sphinx_proof-0.3.0.dist-info/RECORD
